gsearch/__init__.py
gsearch/google/__init__.py
gsearch/google/rich.py
gsearch/google/search.py
gsearch/google/search_image.py
gsearch/google/video.py
ggsearch-1.0.0.dist-info/LICENCE
ggsearch-1.0.0.dist-info/METADATA
ggsearch-1.0.0.dist-info/WHEEL
ggsearch-1.0.0.dist-info/top_level.txt
ggsearch-1.0.0.dist-info/RECORD
