Metadata-Version: 2.1
Name: ggsearch
Version: 1.0.0
Summary: Search with Google
Home-page: https://github.com/Andryerics/gsearch
Author: Andry RL
Author-email: andryerics@gmail.com
License: MIT
Classifier: Programming Language :: Python :: 3
Classifier: License :: OSI Approved :: MIT License
Classifier: Operating System :: OS Independent
Requires-Python: >=3.6
License-File: LICENCE
Requires-Dist: requests
